Single_Port_Asynchronous/sp_ram_async.v
module sram_sp_as #(
    parameter DATA_WIDTH = 8,
    parameter DEPTH = 16
)(
    input clk,
    input we,
    input re,
    input [DATA_WIDTH-1:0] data_in,
    input [$clog2(DEPTH)-1:0] addr,
    output [DATA_WIDTH-1:0] data_out
);

    // Memory array
    reg [DATA_WIDTH-1:0] mem [0:DEPTH-1];

    // Synchronous write
    always @(posedge clk) begin
        if (we)
            mem[addr] <= data_in;
    end

    // Asynchronous read
    assign data_out = (re) ? mem[addr] : {DATA_WIDTH{1'b0}};

endmodule

Single_Port_Asynchronous/sp_ram_async_tb.v
`timescale 1ns/1ps

module sram_sp_as_tb;

    parameter DATA_WIDTH = 8;
    parameter DEPTH = 16;

    reg clk;
    reg we, re;
    reg [DATA_WIDTH-1:0] data_in;
    reg [$clog2(DEPTH)-1:0] addr;

    wire [DATA_WIDTH-1:0] data_out;

    sram_sp_as #(
        .DATA_WIDTH(DATA_WIDTH),
        .DEPTH(DEPTH)
    ) uut (
        .clk(clk),
        .we(we),
        .re(re),
        .data_in(data_in),
        .addr(addr),
        .data_out(data_out)
    );

    // Clock generation
    initial begin
        clk = 0;
        forever #5 clk = ~clk;
    end

    initial begin

        we = 0;
        re = 0;
        addr = 0;
        data_in = 0;

        $dumpfile("sp_ram_async_tb.vcd");
        $dumpvars(0, sram_sp_as_tb);

        //----------------------------
        // Write 25 to address 0
        //----------------------------
        #10;
        addr = 0;
        data_in = 8'd25;
        we = 1;

        #10;
        we = 0;

        //----------------------------
        // Read address 0
        //----------------------------
        #10;
        addr = 0;
        re = 1;

        #10;
        re = 0;

        //----------------------------
        // Write 100 to address 5
        //----------------------------
        #10;
        addr = 5;
        data_in = 8'd100;
        we = 1;

        #10;
        we = 0;

        //----------------------------
        // Read address 5
        //----------------------------
        #10;
        addr = 5;
        re = 1;

        #10;
        re = 0;

        //----------------------------
        // Overwrite address 5
        //----------------------------
        #10;
        addr = 5;
        data_in = 8'd200;
        we = 1;

        #10;
        we = 0;

        //----------------------------
        // Read address 5 again
        //----------------------------
        #10;
        addr = 5;
        re = 1;

        #10;
        re = 0;

        //----------------------------
        // Write 55 to address 15
        //----------------------------
        #10;
        addr = 15;
        data_in = 8'd55;
        we = 1;

        #10;
        we = 0;

        //----------------------------
        // Read address 15
        //----------------------------
        #10;
        addr = 15;
        re = 1;

        #10;
        re = 0;

        #20;
        $finish;

    end

    initial begin
        $monitor("Time=%0t | WE=%b RE=%b | Addr=%0d | Data_in=%0d | Data_out=%0d",
                 $time,we,re,addr,data_in,data_out);
    end

endmodule

Single_Port_Asynchronous/sp_ram_async_tb.vcd
$date
	Mon Jun 29 16:22:25 2026
$end
$version
	Icarus Verilog
$end
$timescale
	1ps
$end
$scope module sram_sp_as_tb $end
$var wire 8 ! data_out [7:0] $end
$var parameter 32 " DATA_WIDTH $end
$var parameter 32 # DEPTH $end
$var reg 4 $ addr [3:0] $end
$var reg 1 % clk $end
$var reg 8 & data_in [7:0] $end
$var reg 1 ' re $end
$var reg 1 ( we $end
$scope module uut $end
$var wire 4 ) addr [3:0] $end
$var wire 1 % clk $end
$var wire 8 * data_in [7:0] $end
$var wire 1 ' re $end
$var wire 1 ( we $end
$var wire 8 + data_out [7:0] $end
$var parameter 32 , DATA_WIDTH $end
$var parameter 32 - DEPTH $end
$upscope $end
$upscope $end
$enddefinitions $end
$comment Show the parameter values. $end
$dumpall
b10000 -
b1000 ,
b10000 #
b1000 "
$end
#0
$dumpvars
b0 +
b0 *
b0 )
0(
0'
b0 &
0%
b0 $
b0 !
$end
#5000
1%
#10000
0%
1(
b11001 &
b11001 *
#15000
1%
#20000
0%
0(
#25000
1%
#30000
b11001 !
b11001 +
0%
1'
#35000
1%
#40000
b0 !
b0 +
0%
0'
#45000
1%
#50000
0%
1(
b1100100 &
b1100100 *
b101 $
b101 )
#55000
1%
#60000
0%
0(
#65000
1%
#70000
b1100100 !
b1100100 +
0%
1'
#75000
1%
#80000
b0 !
b0 +
0%
0'
#85000
1%
#90000
0%
1(
b11001000 &
b11001000 *
#95000
1%
#100000
0%
0(
#105000
1%
#110000
b11001000 !
b11001000 +
0%
1'
#115000
1%
#120000
b0 !
b0 +
0%
0'
#125000
1%
#130000
0%
1(
b110111 &
b110111 *
b1111 $
b1111 )
#135000
1%
#140000
0%
0(
#145000
1%
#150000
b110111 !
b110111 +
0%
1'
#155000
1%
#160000
b0 !
b0 +
0%
0'
